README.md
setup.py
drf_firebase_auth_custom/__init__.py
drf_firebase_auth_custom/apps.py
drf_firebase_auth_custom/authentication.py
drf_firebase_auth_custom/models.py
drf_firebase_auth_custom/settings.py
drf_firebase_auth_custom/utils.py
drf_firebase_auth_custom.egg-info/PKG-INFO
drf_firebase_auth_custom.egg-info/SOURCES.txt
drf_firebase_auth_custom.egg-info/dependency_links.txt
drf_firebase_auth_custom.egg-info/requires.txt
drf_firebase_auth_custom.egg-info/top_level.txt
drf_firebase_auth_custom/migrations/0001_initial.py
drf_firebase_auth_custom/migrations/__init__.py